AUTHORS.rst
CONTRIBUTING.rst
HISTORY.rst
LICENSE
MANIFEST.in
README.rst
setup.cfg
setup.py
docs/Makefile
docs/authors.rst
docs/conf.py
docs/contributing.rst
docs/history.rst
docs/index.rst
docs/installation.rst
docs/make.bat
docs/modules.rst
docs/radegast.rst
docs/readme.rst
docs/usage.rst
radegast/__init__.py
radegast.egg-info/PKG-INFO
radegast.egg-info/SOURCES.txt
radegast.egg-info/dependency_links.txt
radegast.egg-info/not-zip-safe
radegast.egg-info/requires.txt
radegast.egg-info/top_level.txt
tests/test_radegast.py
tests/test_regres.py