Metadata-Version: 2.1
Name: radegast
Version: 0.2.0
Summary: Radegast allow to create simple typed rest clients
Home-page: https://github.com/dswistowski/radegast
Author: Damian Świstowski
Author-email: damian@swistowski.org
License: MIT license
Keywords: radegast
Platform: UNKNOWN
Classifier: Development Status :: 2 - Pre-Alpha
Classifier: Intended Audience :: Developers
Classifier: License :: OSI Approved :: MIT License
Classifier: Natural Language :: English
Classifier: Programming Language :: Python :: 3
Classifier: Programming Language :: Python :: 3.8
Classifier: Programming Language :: Python :: 3.9
Requires-Python: >=3.8
License-File: LICENSE
License-File: AUTHORS.rst
